webevents/__init__.py
webevents/webevents.js
webevents/webevents.py
webevents-0.1.4.dist-info/METADATA
webevents-0.1.4.dist-info/RECORD
webevents-0.1.4.dist-info/WHEEL
webevents-0.1.4.dist-info/top_level.txt
