Metadata-Version: 2.1
Name: webevents
Version: 0.1.4
Summary: A little Python library for making simple HTML/JS GUI apps
Home-page: https://github.com/Zamony/webevents
Author: Nikita Mochalov
Author-email: mochalov.n@ya.ru
License: MIT
Keywords: gui html js events eel electron
Platform: UNKNOWN
Requires-Python: ~=3.6
